setup.py
src/digimat/__init__.py
src/digimat.ccu.egg-info/PKG-INFO
src/digimat.ccu.egg-info/SOURCES.txt
src/digimat.ccu.egg-info/dependency_links.txt
src/digimat.ccu.egg-info/namespace_packages.txt
src/digimat.ccu.egg-info/not-zip-safe
src/digimat.ccu.egg-info/requires.txt
src/digimat.ccu.egg-info/top_level.txt
src/digimat/ccu/__init__.py
src/digimat/ccu/ccu.py