Metadata-Version: 1.0
Name: digimat.ccu
Version: 0.1.18
Summary: Digimat Homematic CCU2
Home-page: UNKNOWN
Author: Frederic Hess
Author-email: fhess@splust.ch
License: PSF
Platform: UNKNOWN
